{
    "tt6769208": {
        "type": "series",
        "description": "David Attenborough returns to the world's oceans in this sequel to the acclaimed documentary filming rare and unusual creatures of the deep, as well as documenting the problems our oceans face.",
        "genres": [
            "Documentary"
        ],
        "ep_map": [
            {
                "episodes": [
                    {
                        "title": "One Ocean",
                        "video": "season/episode/video.mp4",
                        "image": "season/episode/tall.jpg",
                        "description": "",
                        "captions": [
                            {
                                "kind": "captions",
                                "label": "English",
                                "srclang": "en",
                                "src": "season/episode/captions/en.vtt"
                            },
                            {
                                "kind": "captions",
                                "label": "French",
                                "srclang": "fr",
                                "src": "season/episode/captions/fr.vtt"
                            }
                        ]
                    }
                ],
                "title": "Season 1"
            }
        ],
        "tall": "tall.jpg",
        "location": {
            "ipfs": "lksdjfklskdjfk",
            "http": [
                "192.168.1.1:6000/CarsonMedia/Blue Planet II"
            ]
        },
        "title": "Blue Planet II",
        "release_date": "October 21, 2017",
        "rating": 9.4,
        "wide": "wide.jpg",
        "duration": 60
    },
    "tt0327137": {
        "type": "movie",
        "description": "A coming-of-age story about a shy, young boy sent by his irresponsible mother to spend the summer with his wealthy, eccentric uncles in Texas.",
        "genres": [
            "Comedy",
            "Drama",
            "Family"
        ],
        "wide": "wide.jpg",
        "trailer": "video.trailer",
        "title": "Secondhand Lions",
        "duration": 111,
        "rating": 7.6,
        "feature": "mail.mp4",
        "tall": "tall.jpg",
        "release_date": "October 21, 2003",
        "location": {
            "ipfs": "lksdjfklskdjfk",
            "html": [
                "192.168.1.1:6000/CarsonMedia/Secondhand Lions"
            ]
        },
        "captions": {
            "English": "lksjflk",
            "Español": "lkdfj",
            "Français": "lsdfkl"
        }
    }
}